[
  {
    "organism": "std-modifier-group",
    "orbital": "ModifierGroupOrbital",
    "tier": "atoms",
    "factoryPath": "behaviors/functions/app/atoms/std-modifier-group.ts",
    "entities": [
      {
        "name": "ModifierGroupRecord",
        "fields": [
          {
            "name": "name",
            "type": "string",
            "required": true
          },
          {
            "name": "constraintType",
            "type": "string",
            "required": false
          },
          {
            "name": "required",
            "type": "boolean",
            "required": false
          },
          {
            "name": "minSelect",
            "type": "number",
            "required": false
          },
          {
            "name": "maxSelect",
            "type": "number",
            "required": false
          },
          {
            "name": "optionsJson",
            "type": "string",
            "required": false
          }
        ],
        "persistence": "persistent"
      }
    ],
    "traits": [
      {
        "name": "ModifierGroupManage",
        "emittedEvents": [
          "OPEN_GROUP",
          "CLOSE_VIEW",
          "CREATE",
          "UPDATE",
          "DELETE",
          "ModifierGroupLoaded",
          "ModifierGroupLoadFailed",
          "ModifierGroupCreated",
          "ModifierGroupUpdated",
          "ModifierGroupDeleted",
          "ModifierGroupWriteFailed"
        ],
        "listenedEvents": [],
        "overridableConfigKeys": [
          "fields",
          "itemActions",
          "title"
        ],
        "capabilities": []
      }
    ],
    "pages": [
      {
        "name": "ModifierGroupManagePage",
        "defaultPath": "/modifiergroups/manage",
        "primaryEntity": ""
      }
    ],
    "emittedEvents": [
      "CLOSE_VIEW",
      "CREATE",
      "DELETE",
      "ModifierGroupCreated",
      "ModifierGroupDeleted",
      "ModifierGroupLoadFailed",
      "ModifierGroupLoaded",
      "ModifierGroupUpdated",
      "ModifierGroupWriteFailed",
      "OPEN_GROUP",
      "UPDATE"
    ],
    "listenedEvents": [],
    "baseDocument": {
      "type": "document",
      "entities": [
        {
          "type": "entity",
          "name": "ModifierGroupRecord",
          "description": "",
          "fields": [
            {
              "type": "field",
              "name": "name",
              "fieldType": "text",
              "required": true,
              "unique": false,
              "auto": false
            },
            {
              "type": "field",
              "name": "constraintType",
              "fieldType": "text",
              "required": false,
              "unique": false,
              "auto": false
            },
            {
              "type": "field",
              "name": "required",
              "fieldType": "text",
              "required": false,
              "unique": false,
              "auto": false
            },
            {
              "type": "field",
              "name": "minSelect",
              "fieldType": "number",
              "required": false,
              "unique": false,
              "auto": false
            },
            {
              "type": "field",
              "name": "maxSelect",
              "fieldType": "number",
              "required": false,
              "unique": false,
              "auto": false
            },
            {
              "type": "field",
              "name": "optionsJson",
              "fieldType": "text",
              "required": false,
              "unique": false,
              "auto": false
            }
          ],
          "relationships": [],
          "persistence": "persistent",
          "collection": "modifiergroups"
        }
      ],
      "pages": [
        {
          "type": "page",
          "name": "ModifierGroupManagePage",
          "description": "",
          "purpose": "",
          "url": "/modifiergroups/manage",
          "sections": [],
          "actions": [],
          "primaryEntity": "ModifierGroupRecord"
        }
      ],
      "behaviors": []
    }
  }
]
