[
  {
    "organism": "std-rent-charge",
    "orbital": "RentChargeOrbital",
    "tier": "atoms",
    "factoryPath": "behaviors/functions/app/atoms/std-rent-charge.ts",
    "entities": [
      {
        "name": "RentCharge",
        "fields": [
          {
            "name": "tenantId",
            "type": "string",
            "required": true
          },
          {
            "name": "leaseId",
            "type": "string",
            "required": false
          },
          {
            "name": "amount",
            "type": "number",
            "required": false
          },
          {
            "name": "dueDate",
            "type": "string",
            "required": true
          },
          {
            "name": "paidAt",
            "type": "string",
            "required": false
          },
          {
            "name": "status",
            "type": "string",
            "required": false
          },
          {
            "name": "lateFee",
            "type": "number",
            "required": false
          },
          {
            "name": "notes",
            "type": "string",
            "required": false
          }
        ],
        "persistence": "persistent"
      }
    ],
    "traits": [
      {
        "name": "RentChargeLedger",
        "emittedEvents": [
          "OPEN_CHARGE",
          "CLOSE_VIEW",
          "MARK_PAID",
          "ASSESS_LATE_FEE",
          "WAIVE_CHARGE",
          "RentChargeLoaded",
          "RentChargeLoadFailed"
        ],
        "listenedEvents": [],
        "overridableConfigKeys": [
          {
            "key": "fields",
            "type": "[FieldSpec]",
            "default": [
              {
                "label": "Tenant",
                "variant": "caption",
                "name": "tenantId"
              },
              {
                "name": "amount",
                "label": "Amount",
                "variant": "caption"
              },
              {
                "name": "dueDate",
                "label": "Due",
                "variant": "caption"
              },
              {
                "label": "Status",
                "name": "status",
                "variant": "badge"
              },
              {
                "name": "paidAt",
                "variant": "caption",
                "label": "Paid"
              },
              {
                "variant": "caption",
                "label": "Late Fee",
                "name": "lateFee"
              }
            ],
            "label": "Columns to show",
            "description": "Each column maps to one field on the Rent Charge entity",
            "items": {
              "type": "object",
              "properties": {
                "header": {
                  "type": "string",
                  "name": "header",
                  "required": false
                },
                "label": {
                  "type": "string",
                  "name": "label",
                  "required": false
                },
                "key": {
                  "type": "string",
                  "name": "key",
                  "required": false
                },
                "name": {
                  "type": "string",
                  "name": "name",
                  "required": true
                },
                "icon": {
                  "type": "string",
                  "name": "icon",
                  "required": false
                },
                "format": {
                  "type": "string",
                  "name": "format",
                  "required": false
                },
                "variant": {
                  "type": "string",
                  "name": "variant",
                  "required": false
                }
              }
            }
          },
          {
            "key": "itemActions",
            "type": "[ItemAction]",
            "default": [
              {
                "variant": "primary",
                "event": "OPEN_CHARGE",
                "label": "Open",
                "icon": "arrow-right"
              },
              {
                "variant": "danger",
                "label": "Waive",
                "event": "WAIVE_CHARGE"
              }
            ],
            "label": "Row actions",
            "description": "Buttons users can click on each charge row",
            "items": {
              "type": "object",
              "properties": {
                "variant": {
                  "type": "string",
                  "name": "variant",
                  "required": false
                },
                "label": {
                  "type": "string",
                  "name": "label",
                  "required": true
                },
                "event": {
                  "type": "string",
                  "name": "event",
                  "required": true
                },
                "icon": {
                  "type": "string",
                  "name": "icon",
                  "required": false
                }
              }
            }
          },
          {
            "key": "title",
            "type": "string",
            "default": "Rent Charges",
            "label": "Section title",
            "description": "Heading shown above the rent charge ledger"
          }
        ],
        "capabilities": []
      }
    ],
    "pages": [
      {
        "name": "RentChargePage",
        "defaultPath": "/rent-charges",
        "primaryEntity": "RentCharge"
      }
    ],
    "emittedEvents": [
      "ASSESS_LATE_FEE",
      "CLOSE_VIEW",
      "MARK_PAID",
      "OPEN_CHARGE",
      "RentChargeLoadFailed",
      "RentChargeLoaded",
      "WAIVE_CHARGE"
    ],
    "listenedEvents": []
  }
]
