[
  {
    "organism": "ui-divider",
    "orbital": "DividerOrbital",
    "tier": "atoms",
    "factoryPath": "behaviors/functions/ui/core/atoms/ui-divider.ts",
    "entities": [
      {
        "name": "DividerItem",
        "fields": [],
        "persistence": "runtime"
      }
    ],
    "traits": [
      {
        "name": "DividerRender",
        "emittedEvents": [],
        "listenedEvents": [],
        "events": [
          {
            "name": "INIT",
            "direction": "listen"
          }
        ],
        "overridableConfigKeys": [
          {
            "key": "className",
            "type": "string",
            "label": "Class Name",
            "description": "Additional CSS classes",
            "tier": "presentation"
          },
          {
            "key": "label",
            "type": "string",
            "label": "Label",
            "description": "Text label to display in the divider",
            "tier": "presentation"
          },
          {
            "key": "orientation",
            "type": "string",
            "default": "horizontal",
            "label": "Orientation",
            "description": "Orientation of the divider",
            "tier": "presentation",
            "enumValues": [
              "horizontal",
              "vertical"
            ]
          },
          {
            "key": "variant",
            "type": "string",
            "default": "solid",
            "label": "Variant",
            "description": "Line style variant",
            "tier": "presentation",
            "enumValues": [
              "solid",
              "dashed",
              "dotted"
            ]
          }
        ],
        "capabilities": [],
        "transitionEvents": [
          "INIT"
        ],
        "entityRebindable": true,
        "entityContract": {
          "requires": [],
          "provides": []
        }
      }
    ],
    "pages": [
      {
        "name": "DividerPage",
        "defaultPath": "/divider",
        "primaryEntity": "DividerItem"
      }
    ],
    "emittedEvents": [],
    "listenedEvents": [],
    "exposure": "palette",
    "provenance": "generated",
    "sourceValid": true
  }
]
