[
  {
    "organism": "ui-svg-flow",
    "orbital": "SvgFlowOrbital",
    "tier": "atoms",
    "factoryPath": "behaviors/functions/ui/core/atoms/ui-svg-flow.ts",
    "entities": [
      {
        "name": "SvgFlowItem",
        "fields": [],
        "persistence": "runtime"
      }
    ],
    "traits": [
      {
        "name": "SvgFlowRender",
        "emittedEvents": [],
        "listenedEvents": [],
        "events": [
          {
            "name": "INIT",
            "direction": "listen"
          }
        ],
        "overridableConfigKeys": [
          {
            "key": "animated",
            "type": "boolean",
            "default": false,
            "label": "Animated",
            "description": "animated prop",
            "tier": "presentation"
          },
          {
            "key": "asRoot",
            "type": "boolean",
            "default": true,
            "label": "As Root",
            "description": "When true (default), wraps in a standalone <svg> so the shape is visible without a parent SVG context.",
            "tier": "presentation"
          },
          {
            "key": "className",
            "type": "string",
            "default": "",
            "label": "Class Name",
            "description": "className prop",
            "tier": "presentation"
          },
          {
            "key": "color",
            "type": "string",
            "default": "var(--color-primary)",
            "label": "Color",
            "description": "color prop",
            "tier": "presentation"
          },
          {
            "key": "height",
            "type": "number",
            "default": 100,
            "label": "Height",
            "description": "height prop",
            "tier": "presentation"
          },
          {
            "key": "opacity",
            "type": "number",
            "default": 1,
            "label": "Opacity",
            "description": "opacity prop",
            "tier": "presentation"
          },
          {
            "key": "points",
            "type": "[[number]]",
            "default": [],
            "label": "Points",
            "description": "points prop",
            "tier": "presentation",
            "items": {
              "type": "array",
              "items": {
                "type": "number"
              }
            }
          },
          {
            "key": "strokeWidth",
            "type": "number",
            "default": 1.5,
            "label": "Stroke Width",
            "description": "strokeWidth prop",
            "tier": "presentation"
          },
          {
            "key": "width",
            "type": "number",
            "default": 100,
            "label": "Width",
            "description": "width prop",
            "tier": "presentation"
          }
        ],
        "capabilities": [],
        "entityRebindable": true,
        "entityContract": {
          "requires": [],
          "provides": []
        }
      }
    ],
    "pages": [
      {
        "name": "SvgFlowPage",
        "defaultPath": "/svg-flow",
        "primaryEntity": "SvgFlowItem"
      }
    ],
    "emittedEvents": [],
    "listenedEvents": [],
    "exposure": "palette",
    "provenance": "generated"
  }
]
