[
  {
    "organism": "ui-split-pane",
    "orbital": "SplitPaneOrbital",
    "tier": "organisms",
    "factoryPath": "behaviors/functions/ui/core/organisms/ui-split-pane.ts",
    "entities": [
      {
        "name": "SplitPaneItem",
        "fields": [],
        "persistence": "runtime"
      }
    ],
    "traits": [
      {
        "name": "SplitPaneRender",
        "emittedEvents": [],
        "listenedEvents": [],
        "events": [
          {
            "name": "INIT",
            "direction": "listen"
          }
        ],
        "overridableConfigKeys": [
          {
            "key": "className",
            "type": "string",
            "default": "",
            "label": "Class Name",
            "description": "Additional CSS classes",
            "tier": "presentation"
          },
          {
            "key": "direction",
            "type": "string",
            "default": "horizontal",
            "label": "Direction",
            "description": "Direction of the split",
            "tier": "presentation",
            "enumValues": [
              "horizontal",
              "vertical"
            ]
          },
          {
            "key": "leftClassName",
            "type": "string",
            "default": "Left Class Name",
            "label": "Left Class Name",
            "description": "Class for left/top pane",
            "tier": "presentation"
          },
          {
            "key": "minSize",
            "type": "number",
            "default": 100,
            "label": "Min Size",
            "description": "Minimum size of either pane in pixels",
            "tier": "presentation"
          },
          {
            "key": "ratio",
            "type": "number",
            "default": 0,
            "label": "Ratio",
            "description": "Initial ratio (0-100, percentage of first pane)",
            "tier": "presentation"
          },
          {
            "key": "resizable",
            "type": "boolean",
            "default": true,
            "label": "Resizable",
            "description": "Allow user resizing",
            "tier": "presentation"
          },
          {
            "key": "rightClassName",
            "type": "string",
            "default": "Right Class Name",
            "label": "Right Class Name",
            "description": "Class for right/bottom pane",
            "tier": "presentation"
          }
        ],
        "capabilities": [],
        "entityRebindable": true,
        "entityContract": {
          "requires": [],
          "provides": []
        }
      }
    ],
    "pages": [
      {
        "name": "SplitPanePage",
        "defaultPath": "/split-pane",
        "primaryEntity": "SplitPaneItem"
      }
    ],
    "emittedEvents": [],
    "listenedEvents": []
  }
]
