[
  {
    "organism": "std-dashboard-grid-layout",
    "orbital": "DashboardGridLayoutOrbital",
    "tier": "atoms",
    "factoryPath": "behaviors/functions/core/atoms/std-dashboard-grid-layout.ts",
    "entities": [
      {
        "name": "DashboardGridLayoutState",
        "fields": [],
        "persistence": "runtime"
      }
    ],
    "traits": [
      {
        "name": "EmptyTile",
        "emittedEvents": [],
        "listenedEvents": [],
        "overridableConfigKeys": [],
        "capabilities": []
      },
      {
        "name": "DashboardGridLayout",
        "emittedEvents": [],
        "listenedEvents": [],
        "overridableConfigKeys": [
          {
            "key": "appName",
            "type": "string",
            "default": "Dashboard",
            "label": "App name",
            "description": "Product name shown in the dashboard chrome"
          },
          {
            "key": "filter1Trait",
            "type": "trait",
            "default": "@trait.EmptyTile"
          },
          {
            "key": "filter2Trait",
            "type": "trait",
            "default": "@trait.EmptyTile"
          },
          {
            "key": "filter3Trait",
            "type": "trait",
            "default": "@trait.EmptyTile"
          },
          {
            "key": "filter4Trait",
            "type": "trait",
            "default": "@trait.EmptyTile"
          },
          {
            "key": "minTileWidth",
            "type": "number",
            "default": 320,
            "label": "Tile min width",
            "description": "Minimum pixel width per tile before the grid re-flows"
          },
          {
            "key": "navItems",
            "type": "[object]",
            "default": [
              {
                "label": "Dashboard",
                "href": "/dashboard",
                "icon": "bar-chart-3"
              }
            ],
            "label": "Sidebar links",
            "description": "Top-level nav entries on the left rail"
          },
          {
            "key": "tile10Trait",
            "type": "trait",
            "default": "@trait.EmptyTile"
          },
          {
            "key": "tile11Trait",
            "type": "trait",
            "default": "@trait.EmptyTile"
          },
          {
            "key": "tile12Trait",
            "type": "trait",
            "default": "@trait.EmptyTile"
          },
          {
            "key": "tile1Trait",
            "type": "trait",
            "default": "@trait.EmptyTile"
          },
          {
            "key": "tile2Trait",
            "type": "trait",
            "default": "@trait.EmptyTile"
          },
          {
            "key": "tile3Trait",
            "type": "trait",
            "default": "@trait.EmptyTile"
          },
          {
            "key": "tile4Trait",
            "type": "trait",
            "default": "@trait.EmptyTile"
          },
          {
            "key": "tile5Trait",
            "type": "trait",
            "default": "@trait.EmptyTile"
          },
          {
            "key": "tile6Trait",
            "type": "trait",
            "default": "@trait.EmptyTile"
          },
          {
            "key": "tile7Trait",
            "type": "trait",
            "default": "@trait.EmptyTile"
          },
          {
            "key": "tile8Trait",
            "type": "trait",
            "default": "@trait.EmptyTile"
          },
          {
            "key": "tile9Trait",
            "type": "trait",
            "default": "@trait.EmptyTile"
          },
          {
            "key": "toolbar1Trait",
            "type": "trait",
            "default": "@trait.EmptyTile"
          },
          {
            "key": "toolbar2Trait",
            "type": "trait",
            "default": "@trait.EmptyTile"
          },
          {
            "key": "toolbar3Trait",
            "type": "trait",
            "default": "@trait.EmptyTile"
          }
        ],
        "capabilities": []
      }
    ],
    "pages": [
      {
        "name": "DashboardGridLayoutPage",
        "defaultPath": "/dashboard",
        "primaryEntity": "DashboardGridLayoutState"
      }
    ],
    "emittedEvents": [],
    "listenedEvents": []
  }
]
