[
  {
    "organism": "ui-battle-board",
    "orbital": "BattleBoardOrbital",
    "tier": "organisms",
    "factoryPath": "behaviors/functions/ui/game/organisms/ui-battle-board.ts",
    "entities": [
      {
        "name": "BattleBoardItem",
        "fields": [],
        "persistence": "runtime"
      }
    ],
    "traits": [
      {
        "name": "BattleBoardRender",
        "emittedEvents": [
          "HEADER",
          "SIDEBAR",
          "ACTIONS",
          "OVERLAY",
          "GAME_OVER_OVERLAY",
          "ATTACK",
          "GAME_END",
          "UNIT_MOVE",
          "CALCULATE_DAMAGE",
          "DRAW_EFFECTS",
          "RESOLVE_UNIT_FRAME",
          "TILE_CLICK",
          "UNIT_CLICK",
          "END_TURN",
          "CANCEL",
          "PLAY_AGAIN"
        ],
        "listenedEvents": [],
        "events": [
          {
            "name": "HEADER",
            "direction": "emit",
            "description": "-- Slots --",
            "tier": "essential"
          },
          {
            "name": "SIDEBAR",
            "direction": "emit",
            "description": "Sidebar content (combat log, unit roster, etc.)",
            "tier": "essential"
          },
          {
            "name": "ACTIONS",
            "direction": "emit",
            "description": "Floating action buttons",
            "tier": "essential"
          },
          {
            "name": "OVERLAY",
            "direction": "emit",
            "description": "Floating overlays above the canvas (damage popups, tooltips)",
            "tier": "essential"
          },
          {
            "name": "GAME_OVER_OVERLAY",
            "direction": "emit",
            "description": "Game-over screen overlay",
            "tier": "essential"
          },
          {
            "name": "ATTACK",
            "direction": "emit",
            "description": "-- Callbacks --",
            "tier": "essential"
          },
          {
            "name": "GAME_END",
            "direction": "emit",
            "description": "Called when battle ends",
            "tier": "essential"
          },
          {
            "name": "UNIT_MOVE",
            "direction": "emit",
            "description": "Called after a unit moves",
            "tier": "essential"
          },
          {
            "name": "CALCULATE_DAMAGE",
            "direction": "emit",
            "description": "Custom combat damage calculator",
            "tier": "essential"
          },
          {
            "name": "DRAW_EFFECTS",
            "direction": "emit",
            "description": "-- Canvas pass-through --",
            "tier": "essential"
          },
          {
            "name": "RESOLVE_UNIT_FRAME",
            "direction": "emit",
            "description": "resolveUnitFrame prop",
            "tier": "essential"
          },
          {
            "name": "TILE_CLICK",
            "direction": "emit",
            "description": "-- Declarative event props --",
            "tier": "essential"
          },
          {
            "name": "UNIT_CLICK",
            "direction": "emit",
            "description": "Emits UI:{unitClickEvent} with { unitId } on unit click",
            "tier": "essential"
          },
          {
            "name": "END_TURN",
            "direction": "emit",
            "description": "Emits UI:{endTurnEvent} with {} on end turn",
            "tier": "essential"
          },
          {
            "name": "CANCEL",
            "direction": "emit",
            "description": "Emits UI:{cancelEvent} with {} on cancel",
            "tier": "essential"
          },
          {
            "name": "PLAY_AGAIN",
            "direction": "emit",
            "description": "Emits UI:{playAgainEvent} with {} on play again / reset",
            "tier": "essential"
          },
          {
            "name": "INIT",
            "direction": "listen"
          }
        ],
        "overridableConfigKeys": [
          {
            "key": "className",
            "type": "string",
            "default": "",
            "label": "Class Name",
            "description": "className prop",
            "tier": "presentation"
          },
          {
            "key": "effectSpriteUrls",
            "type": "[string]",
            "default": [],
            "label": "Effect Sprite Urls",
            "description": "effectSpriteUrls prop",
            "tier": "presentation",
            "items": {
              "type": "string"
            }
          },
          {
            "key": "hasActiveEffects",
            "type": "boolean",
            "default": false,
            "label": "Has Active Effects",
            "description": "hasActiveEffects prop",
            "tier": "presentation"
          },
          {
            "key": "scale",
            "type": "number",
            "default": 0.45,
            "label": "Scale",
            "description": "Canvas render scale",
            "tier": "presentation"
          },
          {
            "key": "unitScale",
            "type": "number",
            "default": 1,
            "label": "Unit Scale",
            "description": "Unit draw-size multiplier",
            "tier": "presentation"
          }
        ],
        "capabilities": [],
        "entityRebindable": true,
        "entityContract": {
          "requires": [],
          "provides": []
        }
      }
    ],
    "pages": [
      {
        "name": "BattleBoardPage",
        "defaultPath": "/battle-board",
        "primaryEntity": "BattleBoardItem"
      }
    ],
    "emittedEvents": [
      "ACTIONS",
      "ATTACK",
      "CALCULATE_DAMAGE",
      "CANCEL",
      "DRAW_EFFECTS",
      "END_TURN",
      "GAME_END",
      "GAME_OVER_OVERLAY",
      "HEADER",
      "OVERLAY",
      "PLAY_AGAIN",
      "RESOLVE_UNIT_FRAME",
      "SIDEBAR",
      "TILE_CLICK",
      "UNIT_CLICK",
      "UNIT_MOVE"
    ],
    "listenedEvents": []
  }
]
