[
  {
    "organism": "ui-racing-board",
    "orbital": "RacingBoardOrbital",
    "tier": "organisms",
    "factoryPath": "behaviors/functions/ui/game/organisms/ui-racing-board.ts",
    "entities": [
      {
        "name": "RacingBoardItem",
        "fields": [],
        "persistence": "runtime"
      }
    ],
    "traits": [
      {
        "name": "RacingBoardRender",
        "emittedEvents": [
          "TICK",
          "DRAW"
        ],
        "listenedEvents": [],
        "events": [
          {
            "name": "TICK",
            "direction": "emit",
            "description": "Declarative event: emits UI:{tickEvent} with { dt, frame } each tick",
            "tier": "essential"
          },
          {
            "name": "DRAW",
            "direction": "emit",
            "description": "Declarative event: emits UI:{drawEvent} with { frame } each draw frame",
            "tier": "essential"
          },
          {
            "name": "INIT",
            "direction": "listen"
          }
        ],
        "overridableConfigKeys": [
          {
            "key": "activeFilters",
            "type": "json",
            "default": {},
            "label": "Active Filters",
            "description": "Active filters",
            "tier": "presentation"
          },
          {
            "key": "assetBaseUrl",
            "type": "asset",
            "default": "https://almadar-kflow-assets.web.app/shared/",
            "label": "Asset Base Url",
            "description": "Base URL prepended to asset paths",
            "tier": "presentation"
          },
          {
            "key": "backgroundImage",
            "type": "asset",
            "default": "https://almadar-kflow-assets.web.app/shared/backgrounds/bg-parallax/trait-wars/scenes/court.png",
            "label": "Background Image",
            "description": "Race track background image URL",
            "tier": "presentation"
          },
          {
            "key": "className",
            "type": "string",
            "default": "",
            "label": "Class Name",
            "description": "Additional CSS classes",
            "tier": "presentation"
          },
          {
            "key": "error",
            "type": "RacingBoardError",
            "label": "Error",
            "description": "Error state (UiError)",
            "tier": "presentation",
            "properties": {
              "code": {
                "name": "code",
                "required": false,
                "type": "string"
              },
              "message": {
                "name": "message",
                "required": true,
                "type": "string"
              },
              "name": {
                "name": "name",
                "required": false,
                "type": "string"
              },
              "stack": {
                "name": "stack",
                "required": false,
                "type": "string"
              }
            }
          },
          {
            "key": "fps",
            "type": "number",
            "default": 60,
            "label": "FPS",
            "description": "Target frames per second",
            "tier": "presentation"
          },
          {
            "key": "height",
            "type": "number",
            "default": 600,
            "label": "Height",
            "description": "Canvas height in pixels",
            "tier": "presentation"
          },
          {
            "key": "isLoading",
            "type": "boolean",
            "default": false,
            "label": "Is Loading",
            "description": "Loading state indicator",
            "tier": "presentation"
          },
          {
            "key": "pageProp",
            "type": "number",
            "default": 0,
            "label": "Page",
            "description": "Current page number",
            "synonyms": "page",
            "tier": "presentation"
          },
          {
            "key": "pageSize",
            "type": "number",
            "default": 0,
            "label": "Page Size",
            "description": "Number of items per page",
            "tier": "presentation"
          },
          {
            "key": "searchValue",
            "type": "string",
            "default": "Search Value",
            "label": "Search Value",
            "description": "Current search query value",
            "tier": "presentation"
          },
          {
            "key": "selectedIds",
            "type": "[string]",
            "default": [],
            "label": "Selected Ids",
            "description": "Currently selected item IDs",
            "tier": "presentation",
            "items": {
              "type": "string"
            }
          },
          {
            "key": "sortBy",
            "type": "string",
            "default": "Sort By",
            "label": "Sort By",
            "description": "Current sort field",
            "tier": "presentation"
          },
          {
            "key": "sortDirection",
            "type": "string",
            "default": "asc",
            "label": "Sort Direction",
            "description": "Current sort direction",
            "tier": "presentation",
            "enumValues": [
              "asc",
              "desc"
            ]
          },
          {
            "key": "totalCount",
            "type": "number",
            "default": 0,
            "label": "Total Count",
            "description": "Total number of items",
            "tier": "presentation"
          },
          {
            "key": "width",
            "type": "number",
            "default": 800,
            "label": "Width",
            "description": "Canvas width in pixels",
            "tier": "presentation"
          }
        ],
        "capabilities": [],
        "entityRebindable": true,
        "entityContract": {
          "requires": [],
          "provides": []
        }
      }
    ],
    "pages": [
      {
        "name": "RacingBoardPage",
        "defaultPath": "/racing-board",
        "primaryEntity": "RacingBoardItem"
      }
    ],
    "emittedEvents": [
      "DRAW",
      "TICK"
    ],
    "listenedEvents": []
  }
]
