[
  {
    "organism": "std-service-github",
    "orbital": "ServiceGithubOrbital",
    "tier": "atoms",
    "factoryPath": "behaviors/functions/service/atoms/std-service-github.ts",
    "entities": [
      {
        "name": "ServiceGithub",
        "fields": [
          {
            "name": "owner",
            "type": "string",
            "required": false
          },
          {
            "name": "repo",
            "type": "string",
            "required": false
          },
          {
            "name": "path",
            "type": "string",
            "required": false
          },
          {
            "name": "ref",
            "type": "string",
            "required": false
          },
          {
            "name": "result",
            "type": "object",
            "required": false
          },
          {
            "name": "ghStatus",
            "type": "string",
            "required": false
          },
          {
            "name": "error",
            "type": "string",
            "required": false
          },
          {
            "name": "name",
            "type": "string",
            "required": false
          },
          {
            "name": "description",
            "type": "string",
            "required": false
          },
          {
            "name": "status",
            "type": "string",
            "required": false
          }
        ],
        "persistence": "runtime"
      }
    ],
    "traits": [
      {
        "name": "ServiceGithubDefaultForm",
        "emittedEvents": [
          "RUN"
        ],
        "listenedEvents": [],
        "overridableConfigKeys": [],
        "capabilities": []
      },
      {
        "name": "ServiceGithubGithub",
        "emittedEvents": [
          "ServiceGithubLoaded",
          "ServiceGithubLoadFailed",
          "GithubDone",
          "ServiceGithubGithubFailed",
          "FAILED"
        ],
        "listenedEvents": [
          "RUN"
        ],
        "overridableConfigKeys": [
          {
            "key": "op",
            "type": "string",
            "default": "getFile",
            "label": "Operation",
            "description": "Which GitHub action to perform: get file, list commits, or create issue"
          },
          {
            "key": "owner",
            "type": "string",
            "default": "",
            "label": "Owner",
            "description": "GitHub user or organization that owns the repository"
          },
          {
            "key": "path",
            "type": "string",
            "default": "",
            "label": "File path",
            "description": "Path within the repo for file or content operations"
          },
          {
            "key": "ref",
            "type": "string",
            "default": "main",
            "label": "Branch or ref",
            "description": "Branch, tag, or commit SHA the operation runs against"
          },
          {
            "key": "repo",
            "type": "string",
            "default": "",
            "label": "Repository",
            "description": "GitHub repository name the operation targets"
          },
          {
            "key": "uiTrait",
            "type": "trait",
            "default": "@trait.ServiceGithubDefaultForm",
            "label": "Operation form",
            "description": "Trait that renders the GitHub action UI"
          }
        ],
        "capabilities": []
      }
    ],
    "pages": [
      {
        "name": "ServiceGithubPage",
        "defaultPath": "/servicegithubs",
        "primaryEntity": "ServiceGithub"
      }
    ],
    "emittedEvents": [
      "FAILED",
      "GithubDone",
      "RUN",
      "ServiceGithubGithubFailed",
      "ServiceGithubLoadFailed",
      "ServiceGithubLoaded"
    ],
    "listenedEvents": [
      "RUN"
    ]
  }
]
